{"type":"list","cache":true,"reuse":true,"wrap":false,"headline":"Law & Order • Season 22","background":"https://image.tmdb.org/t/p/w1280/tc7canPSAn2X14hYi6Rl3gZm1o4.jpg","template":{"type":"default","layout":"0,0,2,3","area":"0,0,12,6","color":"msx-dark","imageFiller":"cover","imageOverlay":1,"round":1},"items":[{"type":"default","layout":"0,0,2,3","area":"0,0,12,6","image":"https://image.tmdb.org/t/p/w342/1qZwpgVHiOoJv4xoviJtOYpviQ1.jpg","color":"msx-dark","title":"E1 • Gimme Shelter (III)","action":"link:https://mightremoteforever-crypto.github.io/tv-portal/player.html?tmdb=549&s=22&e=1&v=5.7.0","selection":{"important":true,"action":"update:content:underlay:text","data":{"headline":"E1 • Gimme Shelter (III)","text":"A girl is shot and Cosgrove teams with Det. Jalen Shaw to track down her killer. Benson and Stabler assist and realize…"}},"stamp":"E1","stampColor":"msx-yellow"},{"type":"default","layout":"0,0,2,3","area":"0,0,12,6","image":"https://image.tmdb.org/t/p/w342/f9rhiJS56wyLOoezmykkA1DWyLr.jpg","color":"msx-dark","title":"E2 • Battle Lines","action":"link:https://mightremoteforever-crypto.github.io/tv-portal/player.html?tmdb=549&s=22&e=2&v=5.7.0","selection":{"important":true,"action":"update:content:underlay:text","data":{"headline":"E2 • Battle Lines","text":"Things aren't what they seem when a politician's daughter is found dead after an apparent mugging."}},"stamp":"E2","stampColor":"msx-yellow"},{"type":"default","layout":"0,0,2,3","area":"0,0,12,6","image":"https://image.tmdb.org/t/p/w342/xxfDNh5I1t0m07DixwGY9rB2c34.jpg","color":"msx-dark","title":"E3 • Camouflage","action":"link:https://mightremoteforever-crypto.github.io/tv-portal/player.html?tmdb=549&s=22&e=3&v=5.7.0","selection":{"important":true,"action":"update:content:underlay:text","data":{"headline":"E3 • Camouflage","text":"A deadly shooting has Cosgrove and Shaw racing to find the culprit before another attack is orchestrated. Price…"}},"stamp":"E3","stampColor":"msx-yellow"},{"type":"default","layout":"0,0,2,3","area":"0,0,12,6","image":"https://image.tmdb.org/t/p/w342/pTQbVKwGTZrsjpW8oPuD7WwOiq2.jpg","color":"msx-dark","title":"E4 • Benefit of the Doubt","action":"link:https://mightremoteforever-crypto.github.io/tv-portal/player.html?tmdb=549&s=22&e=4&v=5.7.0","selection":{"important":true,"action":"update:content:underlay:text","data":{"headline":"E4 • Benefit of the Doubt","text":"When the young author of a tell-all book is found dead, Cosgrove asks a former mentor for help with the case. Price has…"}},"stamp":"E4","stampColor":"msx-yellow"},{"type":"default","layout":"0,0,2,3","area":"0,0,12,6","image":"https://image.tmdb.org/t/p/w342/rKZS0NwhgKqD1LqlQjSCNpkP4ns.jpg","color":"msx-dark","title":"E5 • 12 Seconds","action":"link:https://mightremoteforever-crypto.github.io/tv-portal/player.html?tmdb=549&s=22&e=5&v=5.7.0","selection":{"important":true,"action":"update:content:underlay:text","data":{"headline":"E5 • 12 Seconds","text":"Cosgrove and Shaw piece together the clues of what happened to a murdered law student, uncovering a web of blackmail…"}},"stamp":"E5","stampColor":"msx-yellow"},{"type":"default","layout":"0,0,2,3","area":"0,0,12,6","image":"https://image.tmdb.org/t/p/w342/hywGTTjmVdlt0E0Cuo45jQvAZLZ.jpg","color":"msx-dark","title":"E6 • Vicious Cycle","action":"link:https://mightremoteforever-crypto.github.io/tv-portal/player.html?tmdb=549&s=22&e=6&v=5.7.0","selection":{"important":true,"action":"update:content:underlay:text","data":{"headline":"E6 • Vicious Cycle","text":"When a fashion designer is killed on the night of his boutique opening, Cosgrove and Shaw must track down a suspect…"}},"stamp":"E6","stampColor":"msx-yellow"},{"type":"default","layout":"0,0,2,3","area":"0,0,12,6","image":"https://image.tmdb.org/t/p/w342/xOps67r1GX2sxqfiXtITDmMhcyt.jpg","color":"msx-dark","title":"E7 • Only the Lonely","action":"link:https://mightremoteforever-crypto.github.io/tv-portal/player.html?tmdb=549&s=22&e=7&v=5.7.0","selection":{"important":true,"action":"update:content:underlay:text","data":{"headline":"E7 • Only the Lonely","text":"A crisis consultant who's made many enemies on behalf of her clients is murdered. Price and Maroun must set aside the…"}},"stamp":"E7","stampColor":"msx-yellow"},{"type":"default","layout":"0,0,2,3","area":"0,0,12,6","image":"https://image.tmdb.org/t/p/w342/tG2A3H2EuxuNdfZaA2UF7W7n8o1.jpg","color":"msx-dark","title":"E8 • Chain of Command","action":"link:https://mightremoteforever-crypto.github.io/tv-portal/player.html?tmdb=549&s=22&e=8&v=5.7.0","selection":{"important":true,"action":"update:content:underlay:text","data":{"headline":"E8 • Chain of Command","text":"When a decorated military veteran is found murdered in his own home, Cosgrove and Shaw work with his daughter to…"}},"stamp":"E8","stampColor":"msx-yellow"},{"type":"default","layout":"0,0,2,3","area":"0,0,12,6","image":"https://image.tmdb.org/t/p/w342/kBidT30k08t8eTEFQRvqNsaFXXh.jpg","color":"msx-dark","title":"E9 • The System","action":"link:https://mightremoteforever-crypto.github.io/tv-portal/player.html?tmdb=549&s=22&e=9&v=5.7.0","selection":{"important":true,"action":"update:content:underlay:text","data":{"headline":"E9 • The System","text":"A suspect arrested for murder escapes police custody after months of waiting for his day in court; as a hostage…"}},"stamp":"E9","stampColor":"msx-yellow"},{"type":"default","layout":"0,0,2,3","area":"0,0,12,6","image":"https://image.tmdb.org/t/p/w342/f7t0aOB2I0MqH9WX2RZo4Y3aLB4.jpg","color":"msx-dark","title":"E10 • Land of Opportunity","action":"link:https://mightremoteforever-crypto.github.io/tv-portal/player.html?tmdb=549&s=22&e=10&v=5.7.0","selection":{"important":true,"action":"update:content:underlay:text","data":{"headline":"E10 • Land of Opportunity","text":"When a homeless migrant is murdered, evidence leads Cosgrove and Shaw to a mysterious cover-up at a construction site.…"}},"stamp":"E10","stampColor":"msx-yellow"},{"type":"default","layout":"0,0,2,3","area":"0,0,12,6","image":"https://image.tmdb.org/t/p/w342/zMgv7kuZTEYFahlOW8kHGvl1k54.jpg","color":"msx-dark","title":"E11 • Second Chance","action":"link:https://mightremoteforever-crypto.github.io/tv-portal/player.html?tmdb=549&s=22&e=11&v=5.7.0","selection":{"important":true,"action":"update:content:underlay:text","data":{"headline":"E11 • Second Chance","text":"When an ex-con is found beaten to death, Cosgrove and Shaw arrest an unlikely culprit. Maroun must put her personal…"}},"stamp":"E11","stampColor":"msx-yellow"},{"type":"default","layout":"0,0,2,3","area":"0,0,12,6","image":"https://image.tmdb.org/t/p/w342/n8SWjJmSZmyaU1VqhsxVVQLwsnE.jpg","color":"msx-dark","title":"E12 • Almost Famous","action":"link:https://mightremoteforever-crypto.github.io/tv-portal/player.html?tmdb=549&s=22&e=12&v=5.7.0","selection":{"important":true,"action":"update:content:underlay:text","data":{"headline":"E12 • Almost Famous","text":"After a teenager is killed, Cosgrove and Shaw discover what lengths kids will go to become internet famous; Price and…"}},"stamp":"E12","stampColor":"msx-yellow"},{"type":"default","layout":"0,0,2,3","area":"0,0,12,6","image":"https://image.tmdb.org/t/p/w342/gDs4exs3HtQqGfWsrq6H3MytmaG.jpg","color":"msx-dark","title":"E13 • Mammon","action":"link:https://mightremoteforever-crypto.github.io/tv-portal/player.html?tmdb=549&s=22&e=13&v=5.7.0","selection":{"important":true,"action":"update:content:underlay:text","data":{"headline":"E13 • Mammon","text":"When a graduate student is found dead, Cosgrove and Shaw follow the evidence to a suspect with no clear motive. Price…"}},"stamp":"E13","stampColor":"msx-yellow"},{"type":"default","layout":"0,0,2,3","area":"0,0,12,6","image":"https://image.tmdb.org/t/p/w342/uWnOfbVeubk4Yb9z3044vbWsdCq.jpg","color":"msx-dark","title":"E14 • Heroes","action":"link:https://mightremoteforever-crypto.github.io/tv-portal/player.html?tmdb=549&s=22&e=14&v=5.7.0","selection":{"important":true,"action":"update:content:underlay:text","data":{"headline":"E14 • Heroes","text":"After shots are fired in a popular nightclub, Cosgrove and Shaw suspect the spree was a ruse to target a sole victim.…"}},"stamp":"E14","stampColor":"msx-yellow"},{"type":"default","layout":"0,0,2,3","area":"0,0,12,6","image":"https://image.tmdb.org/t/p/w342/xC1RHHme7mVtPdoCU8g9MMEQvzp.jpg","color":"msx-dark","title":"E15 • Fear and Loathing","action":"link:https://mightremoteforever-crypto.github.io/tv-portal/player.html?tmdb=549&s=22&e=15&v=5.7.0","selection":{"important":true,"action":"update:content:underlay:text","data":{"headline":"E15 • Fear and Loathing","text":"Cosgrove and Shaw must unravel a string of false crime reports to get to the truth surrounding a respected doctor's…"}},"stamp":"E15","stampColor":"msx-yellow"},{"type":"default","layout":"0,0,2,3","area":"0,0,12,6","image":"https://image.tmdb.org/t/p/w342/slgWNftofLjFUUzGq7yfgtKFDje.jpg","color":"msx-dark","title":"E16 • Deadline","action":"link:https://mightremoteforever-crypto.github.io/tv-portal/player.html?tmdb=549&s=22&e=16&v=5.7.0","selection":{"important":true,"action":"update:content:underlay:text","data":{"headline":"E16 • Deadline","text":"When a celebrated journalist is killed, Cosgrove and Shaw explore an unpublished report involving a prominent…"}},"stamp":"E16","stampColor":"msx-yellow"},{"type":"default","layout":"0,0,2,3","area":"0,0,12,6","image":"https://image.tmdb.org/t/p/w342/qzEMaTrRqKZgfk3muzNyyu54qHw.jpg","color":"msx-dark","title":"E17 • Bias","action":"link:https://mightremoteforever-crypto.github.io/tv-portal/player.html?tmdb=549&s=22&e=17&v=5.7.0","selection":{"important":true,"action":"update:content:underlay:text","data":{"headline":"E17 • Bias","text":"When a public defender is murdered, Cosgrove and Shaw are surprised to find Price at the scene; his involvement in the…"}},"stamp":"E17","stampColor":"msx-yellow"},{"type":"default","layout":"0,0,2,3","area":"0,0,12,6","image":"https://image.tmdb.org/t/p/w342/v1Y3mC5MiBvSqAOyADx50KG40ZT.jpg","color":"msx-dark","title":"E18 • Collateral Damage","action":"link:https://mightremoteforever-crypto.github.io/tv-portal/player.html?tmdb=549&s=22&e=18&v=5.7.0","selection":{"important":true,"action":"update:content:underlay:text","data":{"headline":"E18 • Collateral Damage","text":"When a young woman dies a slow and painful death from an untreated infection, Cosgrove and Shaw suspect she was under…"}},"stamp":"E18","stampColor":"msx-yellow"},{"type":"default","layout":"0,0,2,3","area":"0,0,12,6","image":"https://image.tmdb.org/t/p/w342/dwKwRjnOdqb6L5qo5gzrlLGOeuI.jpg","color":"msx-dark","title":"E19 • Private Lives","action":"link:https://mightremoteforever-crypto.github.io/tv-portal/player.html?tmdb=549&s=22&e=19&v=5.7.0","selection":{"important":true,"action":"update:content:underlay:text","data":{"headline":"E19 • Private Lives","text":"Cosgrove and Shaw investigate the murder of a family physician whose outspoken politician wife suspects she was the…"}},"stamp":"E19","stampColor":"msx-yellow"},{"type":"default","layout":"0,0,2,3","area":"0,0,12,6","image":"https://image.tmdb.org/t/p/w342/8lLhuMYnfWIwlN7rG4ZI5FpLnRY.jpg","color":"msx-dark","title":"E20 • Class Retreat","action":"link:https://mightremoteforever-crypto.github.io/tv-portal/player.html?tmdb=549&s=22&e=20&v=5.7.0","selection":{"important":true,"action":"update:content:underlay:text","data":{"headline":"E20 • Class Retreat","text":"When a respected businessman is found murdered, his surprising connection to Cosgrove's daughter helps the police make…"}},"stamp":"E20","stampColor":"msx-yellow"},{"type":"default","layout":"0,0,2,3","area":"0,0,12,6","image":"https://image.tmdb.org/t/p/w342/kjjqqgHH8RuTZfy9kV2Rp0OE9l4.jpg","color":"msx-dark","title":"E21 • Appraisal","action":"link:https://mightremoteforever-crypto.github.io/tv-portal/player.html?tmdb=549&s=22&e=21&v=5.7.0","selection":{"important":true,"action":"update:content:underlay:text","data":{"headline":"E21 • Appraisal","text":"Cosgrove and Shaw suspect an art dealer was murdered but can't make an arrest until they locate her body. Price and…"}},"stamp":"E21","stampColor":"msx-yellow"},{"type":"default","layout":"0,0,2,3","area":"0,0,12,6","image":"https://image.tmdb.org/t/p/w342/2VVoBy4sitPSftiD4DsugVHDoBx.jpg","color":"msx-dark","title":"E22 • Open Wounds","action":"link:https://mightremoteforever-crypto.github.io/tv-portal/player.html?tmdb=549&s=22&e=22&v=5.7.0","selection":{"important":true,"action":"update:content:underlay:text","data":{"headline":"E22 • Open Wounds","text":"When a senator is gunned down at his daughter's wedding, McCoy pushes for a severe sentence and squares up against a…"}},"stamp":"E22","stampColor":"msx-yellow"}]}