{"type":"list","cache":true,"reuse":true,"wrap":false,"headline":"Silo","background":"https://image.tmdb.org/t/p/w1280/uTWhbLc7Bj4qNSdW3ZvZKL8cOHv.jpg","template":{"type":"default","layout":"0,0,2,3","area":"0,0,12,6","color":"msx-dark","imageFiller":"cover","imageOverlay":1,"round":1},"items":[{"type":"default","layout":"0,0,12,3","area":"0,0,12,3","color":"msx-dark","image":"https://image.tmdb.org/t/p/w1280/uTWhbLc7Bj4qNSdW3ZvZKL8cOHv.jpg","imageFiller":"cover","round":1,"title":"Silo","stamp":"8.2","stampColor":"msx-gold","action":"link:https://mightremoteforever-crypto.github.io/tv-portal/player.html?tmdb=125988&s=1&e=1&v=5.7.1"},{"type":"default","layout":"0,3,12,1.8","area":"0,3,12,1.8","color":"msx-dark","title":"About Silo","text":"In a ruined and toxic future, thousands live in a giant silo deep underground. After its sheriff breaks a cardinal rule and residents die mysteriously, engineer Juliette starts to uncover shocking secrets and the truth about the silo.","separation":0.4,"alignment":"left"},{"type":"button","label":"▶  Play from Season 1, Episode 1","action":"link:https://mightremoteforever-crypto.github.io/tv-portal/player.html?tmdb=125988&s=1&e=1&v=5.7.1"},{"type":"button","label":"Season 1  (10 episodes)","action":"content:https://mightremoteforever-crypto.github.io/tv-portal/content/detail/tv/125988/s1.json?v=5.7.1"},{"type":"button","label":"Season 2  (10 episodes)","action":"content:https://mightremoteforever-crypto.github.io/tv-portal/content/detail/tv/125988/s2.json?v=5.7.1"},{"type":"button","label":"Season 3  (10 episodes)","action":"content:https://mightremoteforever-crypto.github.io/tv-portal/content/detail/tv/125988/s3.json?v=5.7.1"}]}