{"type":"list","cache":true,"reuse":true,"wrap":false,"headline":"Grey's Anatomy • Season 12","background":"https://image.tmdb.org/t/p/w1280/jP0Rhj9OTPDAwQlHQwOLFDdeE8t.jpg","template":{"type":"default","layout":"0,0,2,3","area":"0,0,12,6","color":"msx-dark","imageFiller":"cover","imageOverlay":1,"round":1},"items":[{"type":"default","layout":"0,0,2,3","area":"0,0,12,6","image":"https://image.tmdb.org/t/p/w342/xE71VNd5WMOM0sSqvmiBCvlKQ0M.jpg","title":"E1 • Sledgehammer","action":"link:https://mightremoteforever-crypto.github.io/tv-portal/player.html?tmdb=1416&s=12&e=1&v=5.6.2","selection":{"important":true,"action":"update:content:underlay:text","data":{"headline":"E1 • Sledgehammer","text":"The doctors from Grey Sloan Memorial Hospital spring into action to save the lives of two girls with a powerful story.…"}},"stamp":"E1","stampColor":"msx-yellow"},{"type":"default","layout":"0,0,2,3","area":"0,0,12,6","image":"https://image.tmdb.org/t/p/w342/pvDTmk6BVTsxxF1ILXfSdlWL4Qq.jpg","title":"E2 • Walking Tall","action":"link:https://mightremoteforever-crypto.github.io/tv-portal/player.html?tmdb=1416&s=12&e=2&v=5.6.2","selection":{"important":true,"action":"update:content:underlay:text","data":{"headline":"E2 • Walking Tall","text":"The pressure is on as a determined Bailey tackles her first day as Chief; meanwhile, April's marriage is in jeopardy…"}},"stamp":"E2","stampColor":"msx-yellow"},{"type":"default","layout":"0,0,2,3","area":"0,0,12,6","image":"https://image.tmdb.org/t/p/w342/tLWVf8ML0YYIkkjIHgsD9gVrDOQ.jpg","title":"E3 • I Choose You","action":"link:https://mightremoteforever-crypto.github.io/tv-portal/player.html?tmdb=1416&s=12&e=3&v=5.6.2","selection":{"important":true,"action":"update:content:underlay:text","data":{"headline":"E3 • I Choose You","text":"Maggie reevaluates her life choices after receiving an invitation to her ex-boyfriend’s wedding; Richard questions…"}},"stamp":"E3","stampColor":"msx-yellow"},{"type":"default","layout":"0,0,2,3","area":"0,0,12,6","image":"https://image.tmdb.org/t/p/w342/5f9syT97QFhBdG6TkRiuZvwya7F.jpg","title":"E4 • Old-Time Rock-and-Roll","action":"link:https://mightremoteforever-crypto.github.io/tv-portal/player.html?tmdb=1416&s=12&e=4&v=5.6.2","selection":{"important":true,"action":"update:content:underlay:text","data":{"headline":"E4 • Old-Time Rock-and-Roll","text":"Owen suggests the interns learn a vital lesson on how to break bad news to patients’ families, and Arizona’s…"}},"stamp":"E4","stampColor":"msx-yellow"},{"type":"default","layout":"0,0,2,3","area":"0,0,12,6","image":"https://image.tmdb.org/t/p/w342/7v7t5IGCdUXUScWXvKHtuNbGVPu.jpg","title":"E5 • Guess Who's Coming to Dinner?","action":"link:https://mightremoteforever-crypto.github.io/tv-portal/player.html?tmdb=1416&s=12&e=5&v=5.6.2","selection":{"important":true,"action":"update:content:underlay:text","data":{"headline":"E5 • Guess Who's Coming to Dinner?","text":"In the midst of the sisters’ dinner party, Maggie ditches her cooking duties to rush to the hospital. Meanwhile, April…"}},"stamp":"E5","stampColor":"msx-yellow"},{"type":"default","layout":"0,0,2,3","area":"0,0,12,6","image":"https://image.tmdb.org/t/p/w342/pad7OmhOaI0OarBemjW2VBfGCtt.jpg","title":"E6 • The Me Nobody Knows","action":"link:https://mightremoteforever-crypto.github.io/tv-portal/player.html?tmdb=1416&s=12&e=6&v=5.6.2","selection":{"important":true,"action":"update:content:underlay:text","data":{"headline":"E6 • The Me Nobody Knows","text":"Grey Sloan Memorial not only welcomes a new transfer resident, but also a patient who's the topic of converstation…"}},"stamp":"E6","stampColor":"msx-yellow"},{"type":"default","layout":"0,0,2,3","area":"0,0,12,6","image":"https://image.tmdb.org/t/p/w342/p8Zny56KSosH0tEJGP8GFYBRcFq.jpg","title":"E7 • Something Against You","action":"link:https://mightremoteforever-crypto.github.io/tv-portal/player.html?tmdb=1416&s=12&e=7&v=5.6.2","selection":{"important":true,"action":"update:content:underlay:text","data":{"headline":"E7 • Something Against You","text":"The team of doctors work on a high stakes case of a long time patient, adding additional pressure to an already tense…"}},"stamp":"E7","stampColor":"msx-yellow"},{"type":"default","layout":"0,0,2,3","area":"0,0,12,6","image":"https://image.tmdb.org/t/p/w342/wZgjtndKVmmayyUZoF4Qpg6wdLU.jpg","title":"E8 • Things We Lost in the Fire","action":"link:https://mightremoteforever-crypto.github.io/tv-portal/player.html?tmdb=1416&s=12&e=8&v=5.6.2","selection":{"important":true,"action":"update:content:underlay:text","data":{"headline":"E8 • Things We Lost in the Fire","text":"Midseason Finale -  As the rumor mill around the hospital continues to spiral out of control, Grey Sloan Memorial is…"}},"stamp":"E8","stampColor":"msx-yellow"},{"type":"default","layout":"0,0,2,3","area":"0,0,12,6","image":"https://image.tmdb.org/t/p/w342/a1BUzXp4Mlg1DlXn94bgflrD8Vb.jpg","title":"E9 • The Sound of Silence","action":"link:https://mightremoteforever-crypto.github.io/tv-portal/player.html?tmdb=1416&s=12&e=9&v=5.6.2","selection":{"important":true,"action":"update:content:underlay:text","data":{"headline":"E9 • The Sound of Silence","text":"Meredith is brutally attacked by a patient, and Penny is the one who discovers her. The doctors of Grey Sloan Memorial…"}},"stamp":"E9","stampColor":"msx-yellow"},{"type":"default","layout":"0,0,2,3","area":"0,0,12,6","image":"https://image.tmdb.org/t/p/w342/b2Z4WMsWsDXOI0xyPVpfqB0ia8v.jpg","title":"E10 • All I Want Is You","action":"link:https://mightremoteforever-crypto.github.io/tv-portal/player.html?tmdb=1416&s=12&e=10&v=5.6.2","selection":{"important":true,"action":"update:content:underlay:text","data":{"headline":"E10 • All I Want Is You","text":"Everybody attempts to deals with Meredith's trauma as Maggie and Callie perform a risky, experimental surgery on a…"}},"stamp":"E10","stampColor":"msx-yellow"},{"type":"default","layout":"0,0,2,3","area":"0,0,12,6","image":"https://image.tmdb.org/t/p/w342/4LTdjkdI9hJFMizd5flB2rD4g1U.jpg","title":"E11 • Unbreak My Heart","action":"link:https://mightremoteforever-crypto.github.io/tv-portal/player.html?tmdb=1416&s=12&e=11&v=5.6.2","selection":{"important":true,"action":"update:content:underlay:text","data":{"headline":"E11 • Unbreak My Heart","text":"The evolution of April and Jackson’s relationship is revealed through a series of flashbacks dating back to when they…"}},"stamp":"E11","stampColor":"msx-yellow"},{"type":"default","layout":"0,0,2,3","area":"0,0,12,6","image":"https://image.tmdb.org/t/p/w342/mk2Ru66TLGBSEl5S5Mto21raoEk.jpg","title":"E12 • My Next Life","action":"link:https://mightremoteforever-crypto.github.io/tv-portal/player.html?tmdb=1416&s=12&e=12&v=5.6.2","selection":{"important":true,"action":"update:content:underlay:text","data":{"headline":"E12 • My Next Life","text":"A patient from Meredith's very first surgery as an Intern is readmitted to Grey Sloan Memorial with a new aneurysm, and…"}},"stamp":"E12","stampColor":"msx-yellow"},{"type":"default","layout":"0,0,2,3","area":"0,0,12,6","image":"https://image.tmdb.org/t/p/w342/dBOwY15QuvGIu9dA1sOj6jL12zZ.jpg","title":"E13 • All Eyez on Me","action":"link:https://mightremoteforever-crypto.github.io/tv-portal/player.html?tmdb=1416&s=12&e=13&v=5.6.2","selection":{"important":true,"action":"update:content:underlay:text","data":{"headline":"E13 • All Eyez on Me","text":"Meredith, Bailey, Jackson, Callie and Jo travel to a military hospital to perform an extraordinary and extremely risky…"}},"stamp":"E13","stampColor":"msx-yellow"},{"type":"default","layout":"0,0,2,3","area":"0,0,12,6","image":"https://image.tmdb.org/t/p/w342/wCMC1JYJUJDro5jM3pBordD0GRB.jpg","title":"E14 • Odd Man Out","action":"link:https://mightremoteforever-crypto.github.io/tv-portal/player.html?tmdb=1416&s=12&e=14&v=5.6.2","selection":{"important":true,"action":"update:content:underlay:text","data":{"headline":"E14 • Odd Man Out","text":"There is plenty of turmoil after Richard messes with the staff pairings. Arizona takes a risk to help a woman who is…"}},"stamp":"E14","stampColor":"msx-yellow"},{"type":"default","layout":"0,0,2,3","area":"0,0,12,6","image":"https://image.tmdb.org/t/p/w342/6lWJNxyVJ8F5VZ1EIQFUwnPvn08.jpg","title":"E15 • I Am Not Waiting Anymore","action":"link:https://mightremoteforever-crypto.github.io/tv-portal/player.html?tmdb=1416&s=12&e=15&v=5.6.2","selection":{"important":true,"action":"update:content:underlay:text","data":{"headline":"E15 • I Am Not Waiting Anymore","text":"Jackson learns about April's pregnancy, while Alex and the team of doctors handle an hours-long triple-organ transplant…"}},"stamp":"E15","stampColor":"msx-yellow"},{"type":"default","layout":"0,0,2,3","area":"0,0,12,6","image":"https://image.tmdb.org/t/p/w342/s3YQ71fqcz3kLvy3hWi09ZvgEeY.jpg","title":"E16 • When It Hurts So Bad","action":"link:https://mightremoteforever-crypto.github.io/tv-portal/player.html?tmdb=1416&s=12&e=16&v=5.6.2","selection":{"important":true,"action":"update:content:underlay:text","data":{"headline":"E16 • When It Hurts So Bad","text":"Meredith takes a step forward with Will but quickly regrets it; Maggie senses a disconnection with Andrew; and Amelia…"}},"stamp":"E16","stampColor":"msx-yellow"},{"type":"default","layout":"0,0,2,3","area":"0,0,12,6","image":"https://image.tmdb.org/t/p/w342/aNvABHNLspIQtbIWQy7iZZXXAON.jpg","title":"E17 • I Wear the Face","action":"link:https://mightremoteforever-crypto.github.io/tv-portal/player.html?tmdb=1416&s=12&e=17&v=5.6.2","selection":{"important":true,"action":"update:content:underlay:text","data":{"headline":"E17 • I Wear the Face","text":"Meredith goes on an ambulance ride with Owen and Nathan to pick up a heart for a transplant patient. Musician &amp; MS…"}},"stamp":"E17","stampColor":"msx-yellow"},{"type":"default","layout":"0,0,2,3","area":"0,0,12,6","image":"https://image.tmdb.org/t/p/w342/iuihCDhS1syReQTP3Au1wijuixW.jpg","title":"E18 • There’s a Fine, Fine Line","action":"link:https://mightremoteforever-crypto.github.io/tv-portal/player.html?tmdb=1416&s=12&e=18&v=5.6.2","selection":{"important":true,"action":"update:content:underlay:text","data":{"headline":"E18 • There’s a Fine, Fine Line","text":"After a missing child forces the hospital into lockdown, Ben decides to operate on a pregnant mother without the proper…"}},"stamp":"E18","stampColor":"msx-yellow"},{"type":"default","layout":"0,0,2,3","area":"0,0,12,6","image":"https://image.tmdb.org/t/p/w342/90qwrjig8YpILYWFZkptcsprvRh.jpg","title":"E19 • It’s Alright, Ma (I’m Only Bleeding)","action":"link:https://mightremoteforever-crypto.github.io/tv-portal/player.html?tmdb=1416&s=12&e=19&v=5.6.2","selection":{"important":true,"action":"update:content:underlay:text","data":{"headline":"E19 • It’s Alright, Ma (I’m Only Bleeding)","text":"Miranda continues to deal with the aftermath of Ben's reckless decision and forms an advisory committee to recommend…"}},"stamp":"E19","stampColor":"msx-yellow"},{"type":"default","layout":"0,0,2,3","area":"0,0,12,6","image":"https://image.tmdb.org/t/p/w342/A6g7QoG7LUEffx5j7BM6ZnL7n2d.jpg","title":"E20 • Trigger Happy","action":"link:https://mightremoteforever-crypto.github.io/tv-portal/player.html?tmdb=1416&s=12&e=20&v=5.6.2","selection":{"important":true,"action":"update:content:underlay:text","data":{"headline":"E20 • Trigger Happy","text":"The doctors work frantically to save a young boy who was accidentally shot. Meanwhile, Arizona is upset when Callie…"}},"stamp":"E20","stampColor":"msx-yellow"},{"type":"default","layout":"0,0,2,3","area":"0,0,12,6","image":"https://image.tmdb.org/t/p/w342/83VmhsLHH7JVSedrWMBFYjt8dWF.jpg","title":"E21 • You're Gonna Need Someone on Your Side","action":"link:https://mightremoteforever-crypto.github.io/tv-portal/player.html?tmdb=1416&s=12&e=21&v=5.6.2","selection":{"important":true,"action":"update:content:underlay:text","data":{"headline":"E21 • You're Gonna Need Someone on Your Side","text":"Stephanie’s relationship with Kyle becomes complicated. Meanwhile, Meredith encourages Amelia and Owen to take a chance…"}},"stamp":"E21","stampColor":"msx-yellow"},{"type":"default","layout":"0,0,2,3","area":"0,0,12,6","image":"https://image.tmdb.org/t/p/w342/woSF6krD80hSJERlesIPin0FQx6.jpg","title":"E22 • Mama Tried","action":"link:https://mightremoteforever-crypto.github.io/tv-portal/player.html?tmdb=1416&s=12&e=22&v=5.6.2","selection":{"important":true,"action":"update:content:underlay:text","data":{"headline":"E22 • Mama Tried","text":"Callie and Arizona are at odds over Sofia’s future, and Stephanie questions the status of her relationship with Kyle.…"}},"stamp":"E22","stampColor":"msx-yellow"},{"type":"default","layout":"0,0,2,3","area":"0,0,12,6","image":"https://image.tmdb.org/t/p/w342/2M2MNFhPDH3C9DFAzxeLTlAM18O.jpg","title":"E23 • At Last","action":"link:https://mightremoteforever-crypto.github.io/tv-portal/player.html?tmdb=1416&s=12&e=23&v=5.6.2","selection":{"important":true,"action":"update:content:underlay:text","data":{"headline":"E23 • At Last","text":"Owen and Amelia take their relationship to the next level; Alex gains some clarity on his future with Jo; and Callie…"}},"stamp":"E23","stampColor":"msx-yellow"},{"type":"default","layout":"0,0,2,3","area":"0,0,12,6","image":"https://image.tmdb.org/t/p/w342/bLZ5u888StQ2Qw4oYxiROd0IXRn.jpg","title":"E24 • Family Affair","action":"link:https://mightremoteforever-crypto.github.io/tv-portal/player.html?tmdb=1416&s=12&e=24&v=5.6.2","selection":{"important":true,"action":"update:content:underlay:text","data":{"headline":"E24 • Family Affair","text":"Meredith and Maggie support Amelia on an important day; Jo reveals that she has been keeping secrets from Alex while…"}},"stamp":"E24","stampColor":"msx-yellow"}]}